odoo/addons/website_sale_vat_required/README.rst
odoo/addons/website_sale_vat_required/__init__.py
odoo/addons/website_sale_vat_required/__manifest__.py
odoo/addons/website_sale_vat_required/controllers/__init__.py
odoo/addons/website_sale_vat_required/controllers/main.py
odoo/addons/website_sale_vat_required/i18n/ca.po
odoo/addons/website_sale_vat_required/i18n/es.po
odoo/addons/website_sale_vat_required/i18n/it.po
odoo/addons/website_sale_vat_required/i18n/pt_BR.po
odoo/addons/website_sale_vat_required/i18n/website_sale_vat_required.pot
odoo/addons/website_sale_vat_required/readme/CONTRIBUTORS.md
odoo/addons/website_sale_vat_required/readme/DESCRIPTION.md
odoo/addons/website_sale_vat_required/readme/USAGE.md
odoo/addons/website_sale_vat_required/static/description/icon.png
odoo/addons/website_sale_vat_required/static/description/index.html
odoo/addons/website_sale_vat_required/static/tests/tours/website_sale_vat_required.esm.js
odoo/addons/website_sale_vat_required/tests/__init__.py
odoo/addons/website_sale_vat_required/tests/test_website_sale_vat_required.py
odoo_addon_website_sale_vat_required-18.0.1.0.0.3.dist-info/METADATA
odoo_addon_website_sale_vat_required-18.0.1.0.0.3.dist-info/WHEEL
odoo_addon_website_sale_vat_required-18.0.1.0.0.3.dist-info/top_level.txt
odoo_addon_website_sale_vat_required-18.0.1.0.0.3.dist-info/RECORD
